an_condainitializer/__init__.py
an_condainitializer/condainitializer.py
an_condainitializer-1.0.5.dist-info/LICENSE
an_condainitializer-1.0.5.dist-info/METADATA
an_condainitializer-1.0.5.dist-info/WHEEL
an_condainitializer-1.0.5.dist-info/top_level.txt
an_condainitializer-1.0.5.dist-info/RECORD
