Metadata-Version: 2.1
Name: an_condainitializer
Version: 1.0.5
Summary: A package for an_condainitializer.
Home-page: https://github.com/Atsushi888/Atsushi888
Author: Atsushi888
Author-email: Atsushi888 <vtgrotxu@gmail.com>
Project-URL: Homepage, https://github.com/Atsushi888/an_condainitializer
Project-URL: Repository, https://github.com/Atsushi888/an_condainitializer
Requires-Python: >=3.6
License-File: LICENSE
